vstruct/__init__.py
vstruct/bases.py
vstruct/compat.py
vstruct/types.py
vstruct-2.0.2.dist-info/DESCRIPTION.rst
vstruct-2.0.2.dist-info/METADATA
vstruct-2.0.2.dist-info/metadata.json
vstruct-2.0.2.dist-info/RECORD
vstruct-2.0.2.dist-info/top_level.txt
vstruct-2.0.2.dist-info/WHEEL
