Metadata-Version: 2.0
Name: vstruct
Version: 2.0.2
Summary: Vivisect Structure Definition/Parsing Library
Home-page: https://github.com/vivisect/vstruct
Author: Invisigoth Kenshoto
Author-email: invisigoth.kenshoto@gmail.com
License: Apache License 2.0
Platform: UNKNOWN
Classifier: Development Status :: 5 - Production/Stable
Classifier: License :: OSI Approved :: Apache Software License
Classifier: Programming Language :: Python :: 3.4
Classifier: Programming Language :: Python :: 2.7
